StarWorldCoreLib/__init__.py
StarWorldCoreLib/fileapi.py
StarWorldCoreLib/request.py
StarWorldCoreLib/rstring.py
StarWorldCoreLib/sort.py
StarWorldCoreLib3-1.9.2.dist-info/METADATA
StarWorldCoreLib3-1.9.2.dist-info/WHEEL
StarWorldCoreLib3-1.9.2.dist-info/top_level.txt
StarWorldCoreLib3-1.9.2.dist-info/RECORD
