Metadata-Version: 2.1
Name: StarWorldCoreLib3
Version: 1.9.2
Summary: StarWorldCoreLib
Home-page: https://github.com/WowStarWorld/StarWorldCoreLib3
Author: StarWorld
Author-email: starworldstudio1@gmail.com
License: UNKNOWN
Platform: UNKNOWN
Classifier: Programming Language :: Python :: 3
Classifier: License :: OSI Approved :: MIT License
Classifier: Operating System :: OS Independent
Requires-Python: >=3.8
